joint_ml/__init__.py
joint_ml/_base_client.py
joint_ml/_client_abstract_methods.py
joint_ml/_metric.py
joint_ml/_typing.py
joint_ml/_utils.py
jointml_client-0.2.1.dist-info/WHEEL
jointml_client-0.2.1.dist-info/METADATA
jointml_client-0.2.1.dist-info/RECORD
