Metadata-Version: 2.1
Name: jointml-client
Version: 0.2.1
Summary: The package provides an interface for working with the https://jointml.ru/ platform.
Home-page: https://github.com/joint-ml/client_package
Requires-Python: >=3.9
Classifier: Programming Language :: Python :: 3
Classifier: Programming Language :: Python :: 3.9
Classifier: Programming Language :: Python :: 3.10
Classifier: Programming Language :: Python :: 3.11
Requires-Dist: clint (>=0.5.1,<0.6.0)
Requires-Dist: colorama (>=0.4.6,<0.5.0)
Requires-Dist: pandas (>=2.1.0,<3.0.0)
Requires-Dist: pyfiglet (>=1.0.2,<2.0.0)
Requires-Dist: torch (>=2.0.1,<3.0.0)
Project-URL: Repository, https://github.com/joint-ml/client_package
